{
 "actions": [],
 "allow_rename": 1,
 "creation": "2025-08-27 14:13:28.842886",
 "doctype": "DocType",
 "editable_grid": 1,
 "engine": "InnoDB",
 "field_order": [
  "sales_order",
  "delivered_on",
  "order_total",
  "commission_applied",
  "rto_adjustment"
 ],
 "fields": [
  {
   "fieldname": "sales_order",
   "fieldtype": "Link",
   "label": "Sales Order",
   "options": "Sales Order"
  },
  {
   "fieldname": "delivered_on",
   "fieldtype": "Date",
   "label": "Delivered On"
  },
  {
   "fieldname": "order_total",
   "fieldtype": "Currency",
   "label": "Order Total"
  },
  {
   "fieldname": "commission_applied",
   "fieldtype": "Currency",
   "label": "Commission Applied"
  },
  {
   "fieldname": "rto_adjustment",
   "fieldtype": "Currency",
   "label": "RTO Adjustment"
  }
 ],
 "grid_page_length": 50,
 "index_web_pages_for_search": 1,
 "istable": 1,
 "links": [],
 "modified": "2025-08-27 14:29:10.091452",
 "modified_by": "Administrator",
 "module": "E Commerce",
 "name": "Payout Order Line",
 "owner": "Administrator",
 "permissions": [],
 "row_format": "Dynamic",
 "sort_field": "modified",
 "sort_order": "DESC",
 "states": []
}